README.rst
setup.py
django_rq_mail.egg-info/PKG-INFO
django_rq_mail.egg-info/SOURCES.txt
django_rq_mail.egg-info/dependency_links.txt
django_rq_mail.egg-info/not-zip-safe
django_rq_mail.egg-info/top_level.txt
rq_mail/__init__.py
rq_mail/backends.py
rq_mail/dispatcher.py
rq_mail/models.py
rq_mail/queue.py
rq_mail/settings.py
rq_mail/tasks.py
rq_mail/management/__init__.py
rq_mail/management/commands/__init__.py
rq_mail/management/commands/rq_mail.py