Metadata-Version: 1.0
Name: django-rq-mail
Version: 0.1.3.alpha
Summary: simple Python library based on rq to store emails sent by Django and process them in the background with workers
Home-page: http://github.com/thoas/django-rq-mail
Author: Florent Messa
Author-email: florent.messa@gmail.com
License: UNKNOWN
Platform: UNKNOWN
Classifier: Environment :: Web Environment
Classifier: Intended Audience :: Developers
Classifier: License :: OSI Approved :: MIT License
Classifier: Operating System :: OS Independent
Classifier: Programming Language :: Python
Classifier: Topic :: Utilities
